pyautokakao/__init__.py
pyautokakao/add_friend.py
pyautokakao/invite.py
pyautokakao/make_room.py
pyautokakao/read.py
pyautokakao/send.py
pyautokakao/setup.py
pyautokakao/util.py
pyautokakao-0.0.2.dist-info/LICENSE
pyautokakao-0.0.2.dist-info/METADATA
pyautokakao-0.0.2.dist-info/WHEEL
pyautokakao-0.0.2.dist-info/top_level.txt
pyautokakao-0.0.2.dist-info/RECORD
